{
    	"Name": "Aureolin Fabric",
    	"Description": "A golden cloth that shines like the setting sun. It emits a strong light and a pleasant aura. This fabric appears to be woven from fine and valuable metal, but is far lighter than it should be if so.",
  	"Category": "ArtisanGoods",
  	"CategoryTextOverride": "Mythic Cloth",
  	"Edibility": -300,
  	"Price": 12000,
  	"GiftTastes": 
		{
		"Love": [ "Amanra", "Apples", "Astrid", "Clint", "Coyote", "Dwarf", "Emily", "Gregory", "Hekate", "Hephaestus", "Krobus", "Mephisto", "Morgan", "Puck", "Shuck", "Wednesday", "Alecto", "Wizard", "Xolotl" ],
        	"Like": [ "Abigail", "Alex", "Andy", "Beatrice", "Caroline", "Claire", "Demetrius", "Elliott", "Eloise", "Evelyn", "George", "Gunther", "Gus", "Haley", "Harvey", "Jacob", "Jas", "Jodi", "Kent", "Leah", "Leo", "Lewis", "Linus", "Marlon", "Marnie", "Martin", "Maru", "Morris", "Olivia", "Pam", "Penny", "Pierre", "Robin", "Sam", "Sandy", "Sebastian", "Shane", "Sheila", "Sophia", "Susan", "Victor", "Vincent", "Willy" ],
		},
}
