{
  	"Name": "Honeyberry Juice",
  	"Description": "A bright blue juice made from honey berries. It has an intense flavor reminiscent of a combination of different berries.",
  	"Category": "ArtisanGoods",
  	"CategoryTextOverride": "Fruit Juice",
  	"Edibility": 125,
	"EdibleIsDrink": true,
	"EdibleBuffs":
		{
        	"Farming": 7,
        	"Fishing": 0,
      		"Foraging": 0,
        	"Mining": 0,

        	"Luck": 0,
        	"MaxStamina": 0,
		"MagnetRadius": 0,
        	"Speed": 0,

		"Attack": 0,
        	"Defense": 0,

        	"Duration": 120,
		},
  	"Price": 1125,
  	"IsColored": false,
  	"Recipe": null,
   	"GiftTastes": 
		{
        	"Love": [ "Abigail", "Alex", "Apples", "Beatrice", "Caroline", "Claire", "Clint", "Demetrius", "Dwarf", "Elliott", "Eloise", "Emily", "Evelyn", "George", "Gregory", "Gunther", "Gus", "Haley", "Harvey", "Hekate", "Hephaestus", "Jacob", "Jas", "Jodi", "Kent", "Leah", "Leo", "Lewis", "Linus", "Marlon", "Marnie", "Martin", "Maru", "Morgan", "Morris", "Olivia", "Pam", "Penny", "Pierre", "Robin", "Sam", "Sandy", "Shane", "Sheila", "Sophia", "Susan", "Victor", "Vincent", "Wednesday", "Alecto", "Wizard" ],
		"Neutral": [ "Amanra", "Astrid", "Coyote", "Mephisto", "Puck", "Shuck", "Xolotl" ],
		"Dislike": [ "Krobus", "Willy" ],
		"Hate": [ "Andy", "Sebastian" ]
		},
}
