{
	"Name": "Vanilla Orchid Honey",
	"Description": "An aromatic honey sourced from vanilla orchids. It has a mild vanilla flavor.",
	"Category": "-26",
	"CategoryTextOverride": "Flow Honey",
	"Edibility": 40,
	"EdibleIsDrink": true,
	"Price": 400,
  	"IsColored": false,
  	"Recipe": null,
  	"GiftTastes": 
		{
        	"Like": [ "Abigail", "Alex", "Amanra", "Andy", "Apples", "Astrid", "Beatrice", "Caroline", "Claire", "Clint", "Coyote", "Demetrius", "Dwarf", "Elliott", "Eloise", "Emily", "Evelyn", "George", "Gregory", "Gunther", "Gus", "Haley", "Harvey", "Hekate", "Hephaestus", "Jacob", "Jas", "Jodi", "Kent", "Krobus", "Leah", "Leo", "Lewis", "Linus", "Marlon", "Marnie", "Martin", "Mephisto", "Morgan", "Morris", "Olivia", "Pam", "Penny", "Pierre", "Puck", "Robin", "Sam", "Sandy", "Shane", "Sheila", "Shuck", "Sophia", "Susan", "Victor", "Vincent", "Wednesday", "Willy", "Alecto", "Wizard", "Xolotl" ],
		"Hate": [ "Maru", "Sebastian" ]
		},
	"ContextTags": 
        	[
        	"honey_item"
        	],
}
