{
	"Name": "Elderberry Soda",
  	"Description": "A sweet, carbonated beverage flavored with elderberries. It is an extremely popular refreshment in some parts of the world.",
  	"Category": "ArtisanGoods",
  	"CategoryTextOverride": "Soda Pop",
  	"Edibility": 80,
  	"EdibleIsDrink": true,
  	"Price": 165,
  	"IsColored": false,
  	"Recipe": null,
  	"GiftTastes": 
		{
		"Love": [ "Andy", "Eloise", "Jas", "Leo", "Morgan", "Sam", "Vincent" ],
		"Like": [ "Abigail", "Apples", "Clint", "Emily", "Gus", "Jodi", "Marnie", "Pam", "Penny", "Sebastian", "Shane", "Sheila" ],
		"Neutral": [ "Alex", "Caroline", "Claire", "Gregory", "Kent", "Leah", "Lewis", "Martin", "Maru", "Robin", "Sandy", "Willy" ],
        	"Dislike": [ "Amanra", "Astrid", "Beatrice", "Coyote", "Demetrius", "Elliott", "Evelyn", "Gunther", "Harvey", "Hekate", "Jacob", "Linus", "Marlon", "Mephisto", "Pierre", "Puck", "Shuck", "Sophia", "Susan", "Alecto", "Wizard", "Xolotl" ],
		"Hate": [ "Dwarf", "George", "Haley", "Hephaestus", "Krobus", "Morris", "Olivia", "Victor", "Wednesday" ]
		},
	"DisableWithMod": "Hadi.JASoda",
}
