{
	"Name": "Psilocybin Mushroom",
  	"Description": "A small mushroom with strong hallucinogenic properties. These mushrooms were used medicinally by ancient cultures, and are still used today in certain spiritual ceremonies. They should be treated as a medicine, and are not safe for children to consume.",
  	"Category": "-81",
  	"CategoryTextOverride": "Mushroom",
  	"Edibility": -25,
	"EdibleBuffs":
		{
        	"Farming": 0,
        	"Fishing": 0,
      		"Foraging": 0,
        	"Mining": 0,

        	"Luck": 7,
        	"MaxStamina": -7,
		"MagnetRadius": 0,
        	"Speed": -7,

		"Attack": 0,
        	"Defense": 0,

        	"Duration": 120,
		},
  	"Price": 500,
  	"IsColored": false,
  	"Recipe": null,
  	"GiftTastes": 
		{
		"Love": [ "Amanra", "Astrid", "Clint", "Coyote", "Dwarf", "Emily", "Hekate", "Hephaestus", "Krobus", "Marnie", "Mephisto", "Puck", "Sebastian", "Shuck", "Wednesday", "Alecto", "Wizard", "Xolotl" ],
		"Like": [ "Abigail", "George", "Pam", "Maru", "Sam", "Sandy", "Shane", "Willy" ],
		"Neutral": [ "Morgan" ],
        	"Hate": [ "Alex", "Andy", "Apples", "Beatrice", "Caroline", "Claire", "Demetrius", "Elliott", "Eloise", "Evelyn", "Gregory", "Gunther", "Gus", "Haley", "Harvey", "Jacob", "Jas", "Jodi", "Kent", "Leah", "Leo", "Lewis", "Linus", "Marlon", "Martin", "Morris", "Olivia", "Penny", "Pierre", "Robin", "Sheila", "Sophia", "Susan", "Victor", "Vincent" ],
		},
}
